py3curl.py
py3curl-1.1.3.dist-info/METADATA
py3curl-1.1.3.dist-info/WHEEL
py3curl-1.1.3.dist-info/top_level.txt
py3curl-1.1.3.dist-info/RECORD
