Metadata-Version: 2.1
Name: py3curl
Version: 1.1.3
Summary: 将请求对象转换为curl命令字符串
Home-page: https://github.com/wangjie-jason/py3curl
Author: WangJie
Author-email: 1641540482@qq.com
License: UNKNOWN
Platform: UNKNOWN
Classifier: Programming Language :: Python :: 3
Classifier: License :: OSI Approved :: Apache Software License
Classifier: Operating System :: OS Independent
